formula_math/__init__.py
formula_math/formula_math.py
formula_math-14.0.1.dist-info/licenses/LICENSE
formula_math-14.0.1.dist-info/METADATA
formula_math-14.0.1.dist-info/WHEEL
formula_math-14.0.1.dist-info/top_level.txt
formula_math-14.0.1.dist-info/RECORD
