Metadata-Version: 2.4
Name: formula-math
Version: 14.0.1
Summary: A beginner-friendly Python library for math, finance, geometry, trigonometry, statistics, physics, and helpers
Author: Samarth Chugh
License: MIT
Requires-Python: >=3.6
License-File: LICENSE
Dynamic: license-file
